mud_engine/__init__.py
mud_engine/__main__.py
mud_engine/base.py
mud_engine/commands.py
mud_engine/communication.py
mud_engine/engine.py
mud_engine/events.py
mud_engine/game.py
mud_engine/geography.py
mud_engine/help.py
mud_engine/items.py
mud_engine/npc.py
mud_engine/player.py
mud_engine/version.py
mud_engine/examples/__init__.py
mud_engine/examples/guardian_npc.py
mud_engine/examples/quicksand.py
mud_engine/servers/__init__.py
mud_engine/servers/base.py
mud_engine/servers/telnet.py
mud_engine-1.1.dist-info/METADATA
mud_engine-1.1.dist-info/WHEEL
mud_engine-1.1.dist-info/top_level.txt
mud_engine-1.1.dist-info/RECORD
