Metadata-Version: 2.1
Name: mud-engine
Version: 1.1
Summary: A python based mud engine
Home-page: https://gitlab.com/benjamin.small83/mud-engine
Author: Ben Small
Author-email: benjamin.small83@gmail.com
License: UNKNOWN
Platform: UNKNOWN
Requires-Python: >=3.7
Requires-Dist: ansicolors
